{
  "items": [
    {
      "name": "df",
      "quantity": 2,
      "category": "Stationery",
      "id": 2
    },
    {
      "name": "df",
      "quantity": 3,
      "category": "Stationery",
      "id": 3
    },
    {
      "name": null,
      "quantity": null,
      "category": "Stationery",
      "id": 4,
      "costPerUnit": null
    },
    {
      "name": "Sugar",
      "quantity": 2,
      "category": "Food",
      "costPerUnit": 300,
      "id": 5
    },
    {
      "name": "cads",
      "quantity": 2,
      "category": "Electronics",
      "costPerUnit": 0.02,
      "id": 6
    }
  ]
}